odoo/addons/fs_image/README.rst
odoo/addons/fs_image/__init__.py
odoo/addons/fs_image/__manifest__.py
odoo/addons/fs_image/fields.py
odoo/addons/fs_image/i18n/es.po
odoo/addons/fs_image/i18n/fr.po
odoo/addons/fs_image/i18n/fs_image.pot
odoo/addons/fs_image/i18n/it.po
odoo/addons/fs_image/models/__init__.py
odoo/addons/fs_image/models/fs_image_mixin.py
odoo/addons/fs_image/models/ir_attachment.py
odoo/addons/fs_image/readme/CONTRIBUTORS.md
odoo/addons/fs_image/readme/DESCRIPTION.md
odoo/addons/fs_image/readme/HISTORY.md
odoo/addons/fs_image/readme/USAGE.md
odoo/addons/fs_image/readme/newsfragments/.gitignore
odoo/addons/fs_image/static/description/icon.png
odoo/addons/fs_image/static/description/index.html
odoo/addons/fs_image/static/src/scss/fsimage_field.scss
odoo/addons/fs_image/static/src/views/dialogs/alttext_dialog.esm.js
odoo/addons/fs_image/static/src/views/dialogs/alttext_dialog.xml
odoo/addons/fs_image/static/src/views/fields/fsimage_field.esm.js
odoo/addons/fs_image/static/src/views/fields/fsimage_field.xml
odoo/addons/fs_image/tests/__init__.py
odoo/addons/fs_image/tests/models.py
odoo/addons/fs_image/tests/test_fs_image.py
odoo_addon_fs_image-18.0.1.0.0.2.dist-info/METADATA
odoo_addon_fs_image-18.0.1.0.0.2.dist-info/WHEEL
odoo_addon_fs_image-18.0.1.0.0.2.dist-info/top_level.txt
odoo_addon_fs_image-18.0.1.0.0.2.dist-info/RECORD
